rosdistro_reviewer/__init__.py
rosdistro_reviewer/__main__.py
rosdistro_reviewer/command.py
rosdistro_reviewer/git_lines.py
rosdistro_reviewer/review.py
rosdistro_reviewer/yaml_changes.py
rosdistro_reviewer/yaml_lines.py
rosdistro_reviewer/element_analyzer/__init__.py
rosdistro_reviewer/element_analyzer/rosdep.py
rosdistro_reviewer/element_analyzer/yamllint.py
rosdistro_reviewer/submitter/__init__.py
rosdistro_reviewer/submitter/github.py
rosdistro_reviewer/verb/__init__.py
rosdistro_reviewer/verb/review.py
rosdistro_reviewer-0.1.3.dist-info/METADATA
rosdistro_reviewer-0.1.3.dist-info/WHEEL
rosdistro_reviewer-0.1.3.dist-info/entry_points.txt
rosdistro_reviewer-0.1.3.dist-info/top_level.txt
rosdistro_reviewer-0.1.3.dist-info/zip-safe
rosdistro_reviewer-0.1.3.dist-info/RECORD
