Metadata-Version: 2.1
Name: rosdistro-reviewer
Version: 0.1.3
Summary: Automation for analyzing changes to the rosdep database and rosdistro index
Home-page: UNKNOWN
Author-email: Scott K Logan <logans@cottsay.net>
License: Apache License, Version 2.0
Platform: UNKNOWN
Classifier: Development Status :: 4 - Beta
Classifier: Environment :: Console
Classifier: Intended Audience :: Developers
Classifier: License :: OSI Approved :: Apache Software License
Classifier: Operating System :: MacOS
Classifier: Operating System :: Microsoft :: Windows
Classifier: Operating System :: POSIX
Classifier: Programming Language :: Python
Classifier: Topic :: Software Development :: Testing
Requires-Python: >=3.6
Requires-Dist: colcon-core (>=0.18.0)
Requires-Dist: GitPython
Requires-Dist: rosdep
Requires-Dist: unidiff
Requires-Dist: PyYAML
Requires-Dist: yamllint
Provides-Extra: github
Requires-Dist: PyGithub ; extra == 'github'
Provides-Extra: test
Requires-Dist: flake8 ; extra == 'test'
Requires-Dist: mypy ; extra == 'test'
Requires-Dist: pytest ; extra == 'test'
Requires-Dist: scspell3k (>=2.2) ; extra == 'test'
Requires-Dist: types-PyYAML ; extra == 'test'
